daemons/__init__.py
daemons/cli.py
daemons/db.py
daemons/input_sanitization.py
daemons/legacy_deprecation.py
daemons/logging.py
daemons/main.py
daemons/metrics.py
daemons/models.py
daemons/rate_limit.py
daemons/websocket_security.py
daemons/alembic/README
daemons/alembic/env.py
daemons/alembic/script.py.mako
daemons/alembic/versions/186cf284ed62_items_and_inventory2.py
daemons/alembic/versions/2a6413d60daa_phase11_fields.py
daemons/alembic/versions/4dd9caef62fb_merge_heads_16.py
daemons/alembic/versions/4f2e8d3c1a5b_items_and_inventory.py
daemons/alembic/versions/5a3f9b7e2d1c_npcs_and_ai_framework.py
daemons/alembic/versions/7d4e8f2a3b1c_weapon_stats_for_items.py
daemons/alembic/versions/845936599777_merge_heads.py
daemons/alembic/versions/921a4875c30b_areas.py
daemons/alembic/versions/a1b2c3d4e5f6_phase8_admin_audit.py
daemons/alembic/versions/a68300296648_area_respawn_time_and_npc_override.py
daemons/alembic/versions/b2c3d4e5f6a7_room_types_table.py
daemons/alembic/versions/bc07882b503f_add_room_type_field_to_rooms.py
daemons/alembic/versions/c3d4e5f6a7b8_yaml_managed_rooms.py
daemons/alembic/versions/cc7f91e61ef9_initial_schema.py
daemons/alembic/versions/d9e5f8a7b2c3_quest_progress_and_player_flags.py
daemons/alembic/versions/e1f2a3b4c5d6_phase6_persistence.py
daemons/alembic/versions/ef8829faa761_merge_yaml_rooms_and_phase11_branches.py
daemons/alembic/versions/f7a8b9c0d1e2_phase7_authentication.py
daemons/alembic/versions/g8h9i0j1k2l3_phase9_character_classes.py
daemons/alembic/versions/h1i2j3k4l5m6_account_ban_fields.py
daemons/alembic/versions/i1j2k3l4m5n6_phase10_2_clans.py
daemons/alembic/versions/j2k3l4m5n6o7_phase10_3_factions.py
daemons/alembic/versions/k3l4m5n6o7p8_phase11_light_system.py
daemons/alembic/versions/l4m5n6o7p8q9_phase14_npc_abilities.py
daemons/alembic/versions/m5n6o7p8q9r0_phase14_item_abilities.py
daemons/alembic/versions/n6o7p8q9r0s1_phase16_2_account_lockout.py
daemons/alembic/versions/o7p8q9r0s1t2_door_system.py
daemons_engine-0.1.23.dist-info/licenses/LICENSE
daemons_engine-0.1.23.dist-info/METADATA
daemons_engine-0.1.23.dist-info/WHEEL
daemons_engine-0.1.23.dist-info/entry_points.txt
daemons_engine-0.1.23.dist-info/top_level.txt
daemons_engine-0.1.23.dist-info/RECORD
