Metadata-Version: 2.4
Name: daemons-engine
Version: 0.1.23
Summary: A modern MUD engine - headless game engine for real-time, text-based multiplayer worlds
Author-email: Adam Huston <adamjhuston@gmail.com>
License-Expression: MIT
Project-URL: Homepage, https://github.com/adamhuston/daemons-engine
Project-URL: Documentation, https://github.com/adamhuston/daemons-engine#readme
Project-URL: Repository, https://github.com/adamhuston/daemons-engine.git
Project-URL: Issues, https://github.com/adamhuston/daemons-engine/issues
Keywords: mud,game-engine,rpg,multiplayer,websocket,fastapi
Classifier: Development Status :: 4 - Beta
Classifier: Environment :: Console
Classifier: Framework :: FastAPI
Classifier: Intended Audience :: Developers
Classifier: Operating System :: OS Independent
Classifier: Programming Language :: Python :: 3
Classifier: Programming Language :: Python :: 3.11
Classifier: Programming Language :: Python :: 3.12
Classifier: Programming Language :: Python :: 3.13
Classifier: Topic :: Games/Entertainment :: Multi-User Dungeons (MUD)
Classifier: Topic :: Games/Entertainment :: Role-Playing
Classifier: Typing :: Typed
Requires-Python: >=3.11
License-File: LICENSE
Requires-Dist: aiofiles>=24.1.0
Requires-Dist: aiosqlite>=0.21.0
Requires-Dist: alembic>=1.13.1
Requires-Dist: argon2-cffi>=23.1.0
Requires-Dist: click>=8.3.1
Requires-Dist: colorama>=0.4.6
Requires-Dist: fastapi>=0.122.0
Requires-Dist: httpx>=0.28.1
Requires-Dist: passlib[argon2]>=1.7.4
Requires-Dist: prometheus-client>=0.22.1
Requires-Dist: pydantic>=2.12.5
Requires-Dist: python-dotenv>=1.2.1
Requires-Dist: python-jose[cryptography]>=3.4.0
Requires-Dist: PyYAML>=6.0.3
Requires-Dist: SQLAlchemy>=2.0.44
Requires-Dist: slowapi>=0.1.9
Requires-Dist: structlog>=25.3.0
Requires-Dist: uvicorn[standard]>=0.38.0
Requires-Dist: websockets>=15.0.1
Provides-Extra: dev
Requires-Dist: pytest>=7.0.0; extra == "dev"
Requires-Dist: pytest-asyncio>=0.21.0; extra == "dev"
Requires-Dist: pytest-cov>=4.0.0; extra == "dev"
Requires-Dist: pytest-timeout>=2.0.0; extra == "dev"
Requires-Dist: pytest-xdist>=3.0.0; extra == "dev"
Requires-Dist: pre-commit>=3.0.0; extra == "dev"
Requires-Dist: ruff>=0.1.0; extra == "dev"
Requires-Dist: black>=23.0.0; extra == "dev"
Requires-Dist: isort>=5.12.0; extra == "dev"
Requires-Dist: mypy>=1.0.0; extra == "dev"
Requires-Dist: safety>=2.0.0; extra == "dev"
Provides-Extra: client
Requires-Dist: flet>=0.21.0; extra == "client"
Dynamic: license-file
